dummy/__init__.py
dummy/input.py
dummy/model.py
ioflow/__init__.py
ioflow/shortcut.py
ioflow/utils.py
ioflow/configure/__init__.py
ioflow/configure/get_configure_path_from_argv.py
ioflow/configure/read_configure.py
ioflow/corpus/__init__.py
ioflow/corpus_processor/__init__.py
ioflow/corpus_processor/corpus_processor_base.py
ioflow/corpus_processor/download_corpus_processor.py
ioflow/corpus_processor/download_file.py
ioflow/corpus_processor/http_corpus_processor.py
ioflow/corpus_processor/local_corpus_processor.py
ioflow/corpus_processor/raw_corpus_processor.py
ioflow/eval_reporter/__init__.py
ioflow/helper/__init__.py
ioflow/helper/fasttext_parser.py
ioflow/hooks/__init__.py
ioflow/hooks/db_task_manager.py
ioflow/hooks/local_task_manager.py
ioflow/hooks/task_manager.py
ioflow/model_saver/__init__.py
ioflow/model_saver/http_based_model_saver.py
ioflow/model_saver/local_model_saver.py
ioflow/model_saver/model_saver_base.py
ioflow/performance_metrics/__init__.py
ioflow/performance_reporter/__init__.py
ioflow/performance_reporter/db_performance_reporter.py
ioflow/performance_reporter/local_performance_reporter.py
ioflow/performance_reporter/metric.py
ioflow/performance_reporter/performance.py
ioflow/performance_reporter/performance_reporter_base.py
ioflow/task_manager/__init__.py
ioflow/task_manager/daemon_based_task_manager.py
ioflow/task_manager/db_task_manager.py
ioflow/task_manager/local_task_manager.py
ioflow/task_manager/task_manager.py
ioflow/task_manager/task_manager_base.py
ioflow/task_manager/status_controller/__init__.py
ioflow/task_manager/status_controller/db_status_controller.py
ioflow/task_manager/status_controller/local_status_controller.py
ioflow/task_manager/status_controller/status_controller_base.py
ioflow/task_status/__init__.py
ioflow/watchers/__init__.py
tests/__init__.py
tests/utils.py
tests/corpus_processor/__init__.py
tests/corpus_processor/test_download_corpus_processor.py
tests/corpus_processor/test_download_file.py
ioflow-0.11.2.dist-info/LICENSE
ioflow-0.11.2.dist-info/METADATA
ioflow-0.11.2.dist-info/WHEEL
ioflow-0.11.2.dist-info/top_level.txt
ioflow-0.11.2.dist-info/RECORD
