Metadata-Version: 2.1
Name: ioflow
Version: 0.11.2
Summary: Input/Output abstraction layer for machine learning
Home-page: https://github.com/howl-anderson/ioflow
Author: Xiaoquan Kong
Author-email: u1mail2me@gmail.com
License: Apache 2.0
Platform: UNKNOWN
Requires-Dist: numpy
Requires-Dist: requests
Requires-Dist: flask
Requires-Dist: scikit-learn
Requires-Dist: jsonlines
Requires-Dist: pconf
Requires-Dist: tokenizer-tools
Requires-Dist: tf-summary-reader
Requires-Dist: tensorflow (<2.0.0,>=1.15.0)
Requires-Dist: nlp-utils
